MANIFEST.in
README.md
setup.py
Eureqa.egg-info/PKG-INFO
Eureqa.egg-info/SOURCES.txt
Eureqa.egg-info/dependency_links.txt
Eureqa.egg-info/requires.txt
Eureqa.egg-info/top_level.txt
analysis_templates/__init__.py
analysis_templates/example_module/__init__.py
docs/source/examples/double_pendulum_test.csv
docs/source/examples/double_pendulum_train.csv
docs/source/examples/nutrition.csv
docs/source/examples/sales_marketing.csv
eureqa/__init__.py
eureqa/__main__.py
eureqa/apply_solution_result.py
eureqa/complexity_weights.py
eureqa/data_source.py
eureqa/data_splitting.py
eureqa/error_metric.py
eureqa/eureqa.py
eureqa/install_analysis_template.py
eureqa/math_block.py
eureqa/math_block_set.py
eureqa/missing_value_policies.py
eureqa/model_evaluation.py
eureqa/organization.py
eureqa/passwords.py
eureqa/run_analysis_template.py
eureqa/search.py
eureqa/search_settings.py
eureqa/search_templates.py
eureqa/session.py
eureqa/solution.py
eureqa/variable_details.py
eureqa/variable_options.py
eureqa/variable_options_dict.py
eureqa/versions.py
eureqa/analysis/__init__.py
eureqa/analysis/analysis_file.py
eureqa/analysis/cards.py
eureqa/analysis/components/__init__.py
eureqa/analysis/components/base.py
eureqa/analysis/components/binned_mean_plot.py
eureqa/analysis/components/box_plot.py
eureqa/analysis/components/by_row_plot.py
eureqa/analysis/components/custom_plot.py
eureqa/analysis/components/distribution_plot.py
eureqa/analysis/components/double_histogram_plot.py
eureqa/analysis/components/download_file.py
eureqa/analysis/components/dropdown_layout.py
eureqa/analysis/components/formatted_text.py
eureqa/analysis/components/html_block.py
eureqa/analysis/components/image.py
eureqa/analysis/components/layout.py
eureqa/analysis/components/magnitude_bar.py
eureqa/analysis/components/modal.py
eureqa/analysis/components/modal_link.py
eureqa/analysis/components/model.py
eureqa/analysis/components/model_evaluator.py
eureqa/analysis/components/model_fit_by_row_plot.py
eureqa/analysis/components/model_fit_separation_plot.py
eureqa/analysis/components/model_summary.py
eureqa/analysis/components/model_terms_plot.py
