Metadata-Version: 1.0
Name: Eureqa
Version: 1.76.0
Summary: Nutonian Eureqa API
Home-page: http://nutonian.com/
Author: Nutonian
Author-email: contact@nutonian.com
License: UNKNOWN
Platform: UNKNOWN
